password_safe_api_client/__init__.py
password_safe_api_client/client.py
password_safe_api_client/models/__init__.py
password_safe_api_client/models/exceptions.py
password_safe_api_client/models/managed_account.py
password_safe_api_client/models/query.py
tests/__init__.py
tests/test_authentication.py
tests/test_managed_accounts.py
tests/test_managed_systems.py
tests/test_posts.py
tests/extras/__init__.py
password_safe_api_client-0.1.0.dist-info/LICENSE.md
password_safe_api_client-0.1.0.dist-info/METADATA
password_safe_api_client-0.1.0.dist-info/WHEEL
password_safe_api_client-0.1.0.dist-info/entry_points.txt
password_safe_api_client-0.1.0.dist-info/top_level.txt
password_safe_api_client-0.1.0.dist-info/zip-safe
password_safe_api_client-0.1.0.dist-info/RECORD
