Metadata-Version: 2.1
Name: password-safe-api-client
Version: 0.1.0
Summary: Password Safe API Client Library
Home-page: https://pypi.org/project/password-safe-api-client/
Author: Jerod Gawne
Author-email: jerod@jerodg.dev
License: Server Side Public License (SSPL)
Project-URL: Bugs, https://github.com/jerodg/password-safe-api-client/issues
Project-URL: Documentation, https://jerodg.github.io/password-safe-api-client
Project-URL: Funding, https://www.paypal.me/jerodgawne
Project-URL: Say Thanks!, https://saythanks.io/to/jerodg
Project-URL: Source, https://github.com/jerodg/password-safe-api-client
Keywords: Password Safe API Client rest
Platform: UNKNOWN
Classifier: Development Status :: 5 - Production/Stable
Classifier: Environment :: Console
Classifier: Intended Audience :: End Users/Desktop
Classifier: Intended Audience :: Developers
Classifier: Intended Audience :: System Administrators
Classifier: License :: Other/Proprietary License
Classifier: Natural Language :: English
Classifier: Operating System :: MacOS :: MacOS X
Classifier: Operating System :: Microsoft :: Windows
Classifier: Operating System :: POSIX
Classifier: Programming Language :: Python :: 3.8
Classifier: Topic :: Utilities
Classifier: Topic :: Internet
Classifier: Topic :: Internet :: WWW/HTTP
Requires-Python: >=3.8, <3.9
Requires-Dist: base-api-client
